{
  "id": "742e671e-d09c-44ee-9594-fceae32fbaeb",
  "prevId": "11bbff94-d7b1-4710-bd9d-4d0b7368bf8e",
  "version": "7",
  "dialect": "postgresql",
  "tables": {
    "public.categories": {
      "name": "categories",
      "schema": "",
      "columns": {
        "id": {
          "name": "id",
          "type": "serial",
          "primaryKey": true,
          "notNull": true
        },
        "name": {
          "name": "name",
          "type": "varchar(50)",
          "primaryKey": false,
          "notNull": true
        },
        "created_at": {
          "name": "created_at",
          "type": "timestamp",
          "primaryKey": false,
          "notNull": true,
          "default": "now()"
        },
        "updated_at": {
          "name": "updated_at",
          "type": "timestamp",
          "primaryKey": false,
          "notNull": true,
          "default": "now()"
        }
      },
      "indexes": {},
      "foreignKeys": {},
      "compositePrimaryKeys": {},
      "uniqueConstraints": {
        "categories_name_unique": {
          "name": "categories_name_unique",
          "nullsNotDistinct": false,
          "columns": [
            "name"
          ]
        }
      }
    },
    "public.projects": {
      "name": "projects",
      "schema": "",
      "columns": {
        "id": {
          "name": "id",
          "type": "serial",
          "primaryKey": true,
          "notNull": true
        },
        "title": {
          "name": "title",
          "type": "varchar(255)",
          "primaryKey": false,
          "notNull": true
        },
        "description": {
          "name": "description",
          "type": "text",
          "primaryKey": false,
          "notNull": true
        },
        "achievements": {
          "name": "achievements",
          "type": "text[]",
          "primaryKey": false,
          "notNull": true
        },
        "repo_url": {
          "name": "repo_url",
          "type": "varchar(255)",
          "primaryKey": false,
          "notNull": false
        },
        "image_url": {
          "name": "image_url",
          "type": "varchar(255)",
          "primaryKey": false,
          "notNull": false
        },
        "site_url": {
          "name": "site_url",
          "type": "varchar(255)",
          "primaryKey": false,
          "notNull": false
        },
        "start_date": {
          "name": "start_date",
          "type": "timestamp",
          "primaryKey": false,
          "notNull": false
        },
        "end_date": {
          "name": "end_date",
          "type": "timestamp",
          "primaryKey": false,
          "notNull": false
        },
        "is_public": {
          "name": "is_public",
          "type": "boolean",
          "primaryKey": false,
          "notNull": true,
          "default": true
        },
        "created_at": {
          "name": "created_at",
          "type": "timestamp",
          "primaryKey": false,
          "notNull": true,
          "default": "now()"
        },
        "updated_at": {
          "name": "updated_at",
          "type": "timestamp",
          "primaryKey": false,
          "notNull": true,
          "default": "now()"
        }
      },
      "indexes": {},
      "foreignKeys": {},
      "compositePrimaryKeys": {},
      "uniqueConstraints": {}
    },
    "public.technologies": {
      "name": "technologies",
      "schema": "",
      "columns": {
        "id": {
          "name": "id",
          "type": "serial",
          "primaryKey": true,
          "notNull": true
        },
        "name": {
          "name": "name",
          "type": "varchar(100)",
          "primaryKey": false,
          "notNull": true
        },
        "category_id": {
          "name": "category_id",
          "type": "integer",
          "primaryKey": false,
          "notNull": true
        },
        "description": {
          "name": "description",
          "type": "text",
          "primaryKey": false,
          "notNull": false
        },
        "icon_url": {
          "name": "icon_url",
          "type": "varchar(255)",
          "primaryKey": false,
          "notNull": false
        },
        "color": {
          "name": "color",
          "type": "varchar(20)",
          "primaryKey": false,
          "notNull": false
        },
        "is_active": {
          "name": "is_active",
          "type": "boolean",
          "primaryKey": false,
          "notNull": true,
          "default": true
        },
        "created_at": {
          "name": "created_at",
          "type": "timestamp",
          "primaryKey": false,
          "notNull": true,
          "default": "now()"
        },
        "updated_at": {
          "name": "updated_at",
          "type": "timestamp",
          "primaryKey": false,
          "notNull": true,
          "default": "now()"
        }
      },
      "indexes": {
        "idx_tech_cat_id": {
          "name": "idx_tech_cat_id",
          "columns": [
            {
              "expression": "category_id",
              "isExpression": false,
              "asc": true,
              "nulls": "last"
            }
          ],
          "isUnique": false,
          "concurrently": false,
          "method": "btree",
          "with": {}
        },
        "idx_tech_is_active": {
          "name": "idx_tech_is_active",
          "columns": [
            {
              "expression": "is_active",
              "isExpression": false,
              "asc": true,
              "nulls": "last"
            }
          ],
          "isUnique": false,
          "concurrently": false,
          "method": "btree",
          "with": {}
        }
      },
      "foreignKeys": {
        "technologies_category_id_categories_id_fk": {
          "name": "technologies_category_id_categories_id_fk",
          "tableFrom": "technologies",
          "tableTo": "categories",
          "columnsFrom": [
            "category_id"
          ],
          "columnsTo": [
            "id"
          ],
          "onDelete": "no action",
          "onUpdate": "no action"
        }
      },
      "compositePrimaryKeys": {},
      "uniqueConstraints": {
        "technologies_name_unique": {
          "name": "technologies_name_unique",
          "nullsNotDistinct": false,
          "columns": [
            "name"
          ]
        }
      }
    },
    "public.project_technologies": {
      "name": "project_technologies",
      "schema": "",
      "columns": {
        "project_id": {
          "name": "project_id",
          "type": "integer",
          "primaryKey": false,
          "notNull": false
        },
        "technology_id": {
          "name": "technology_id",
          "type": "integer",
          "primaryKey": false,
          "notNull": false
        }
      },
      "indexes": {
        "idx_pt_project_id": {
          "name": "idx_pt_project_id",
          "columns": [
            {
              "expression": "project_id",
              "isExpression": false,
              "asc": true,
              "nulls": "last"
            }
          ],
          "isUnique": false,
          "concurrently": false,
          "method": "btree",
          "with": {}
        },
        "idx_pt_tech_id": {
          "name": "idx_pt_tech_id",
          "columns": [
            {
              "expression": "technology_id",
              "isExpression": false,
              "asc": true,
              "nulls": "last"
            }
          ],
          "isUnique": false,
          "concurrently": false,
          "method": "btree",
          "with": {}
        }
      },
      "foreignKeys": {
        "project_technologies_project_id_projects_id_fk": {
          "name": "project_technologies_project_id_projects_id_fk",
          "tableFrom": "project_technologies",
          "tableTo": "projects",
          "columnsFrom": [
            "project_id"
          ],
          "columnsTo": [
            "id"
          ],
          "onDelete": "no action",
          "onUpdate": "no action"
        },
        "project_technologies_technology_id_technologies_id_fk": {
          "name": "project_technologies_technology_id_technologies_id_fk",
          "tableFrom": "project_technologies",
          "tableTo": "technologies",
          "columnsFrom": [
            "technology_id"
          ],
          "columnsTo": [
            "id"
          ],
          "onDelete": "no action",
          "onUpdate": "no action"
        }
      },
      "compositePrimaryKeys": {},
      "uniqueConstraints": {}
    },
    "public.skills": {
      "name": "skills",
      "schema": "",
      "columns": {
        "id": {
          "name": "id",
          "type": "serial",
          "primaryKey": true,
          "notNull": true
        },
        "technology_id": {
          "name": "technology_id",
          "type": "integer",
          "primaryKey": false,
          "notNull": true
        },
        "level": {
          "name": "level",
          "type": "integer",
          "primaryKey": false,
          "notNull": true,
          "default": 0
        },
        "created_at": {
          "name": "created_at",
          "type": "timestamp",
          "primaryKey": false,
          "notNull": true,
          "default": "now()"
        },
        "updated_at": {
          "name": "updated_at",
          "type": "timestamp",
          "primaryKey": false,
          "notNull": true,
          "default": "now()"
        }
      },
      "indexes": {
        "idx_skills_tech_id": {
          "name": "idx_skills_tech_id",
          "columns": [
            {
              "expression": "technology_id",
              "isExpression": false,
              "asc": true,
              "nulls": "last"
            }
          ],
          "isUnique": false,
          "concurrently": false,
          "method": "btree",
          "with": {}
        }
      },
      "foreignKeys": {
        "skills_technology_id_technologies_id_fk": {
          "name": "skills_technology_id_technologies_id_fk",
          "tableFrom": "skills",
          "tableTo": "technologies",
          "columnsFrom": [
            "technology_id"
          ],
          "columnsTo": [
            "id"
          ],
          "onDelete": "no action",
          "onUpdate": "no action"
        }
      },
      "compositePrimaryKeys": {},
      "uniqueConstraints": {}
    }
  },
  "enums": {},
  "schemas": {},
  "sequences": {},
  "_meta": {
    "columns": {},
    "schemas": {},
    "tables": {}
  }
}